Workbook

Sheet START HERE
A1: CMAP 2026 — Week 3 Evaluation Template
A2: Owner: Maksim (Finance & Evaluation Analyst)
A4: PURPOSE | B4: Capture the model's answers, score them against the gold standard, and auto-produce the Accuracy Report and RAG Comparison Results.
A6: THE ORDER OF WORK
A7: Step 1 | B7: Run the RAG pipeline over the 100 benchmark questions. Export its answers.
A8: Step 2 | B8: Paste those answers into the 'ModelAnswers' sheet (yellow columns only). One row per question, per config.
A9: Step 3 | B9: Go to 'Evaluation'. The question, gold answer and model answer pull through automatically. You fill in Score (1-4) and Rationale.
A10: Step 4 | B10: 'AccuracyReport' updates itself — average score, score distribution, per-lender and per-category breakdown, retrieval hit rate.
A11: Step 5 | B11: Repeat Steps 1-4 for each RAG config, then record the headline numbers in 'RAG_Comparison'.
A13: COLOUR KEY
A14: Yellow cells | B14: You type here (manual input).
A15: Blue cells | B15: Auto-calculated by formula — do not overwrite.
A17: THE GOLDEN RULE | B17: Every row's 'Source Chunk ID' must exist in Metadata.csv. If the model cites a chunk that isn't there, the answer is not grounded.
A19: SCORING RUBRIC
A20: 4 / 4 | B20: Completely right — fully correct and complete.
A21: 3 / 4 | B21: Correct overall, but contains minor mistakes (e.g. one wrong figure).
A22: 2 / 4 | B22: Incorrect in general, but contains some true information.
A23: 1 / 4 | B23: Completely wrong — the information is incorrect.
A25: RETRIEVAL vs ANSWER | B25: Two different things are measured. 'Retrieval Hit' asks: did the system fetch the right chunk? 'Score' asks: was the final answer correct? A model can retrieve the right chunk and still answer badly — and vice versa.
A27: FILES THIS CONNECTS TO | B27: QuestionBank.xlsx (the 100 questions) · GroundTruth.xlsx (scored examples) · Metadata.csv (chunk tags)

Sheet ModelAnswers
A1: ID | B1: Lender | C1: Category | D1: Question | E1: Config Name | F1: Model Answer | G1: Retrieved Chunk ID | H1: Response Time (s) | I1: Tokens Used | J1: Est. Cost (USD)
A2: RES-01 | B2: Resimac | C2: ELIGIBILITY | D2: What minimum ABN and GST registration duration does Resimac's PremiumPLUS tier require? | E2: v4: gpt-4o-mini + union retrieval (lender OR lender+intent) | F2: Resimac's PremiumPLUS tier requires a minimum ABN duration of greater than 6 years and a minimum GST registration duration of greater than 3 years. (chunk_id: resimac_customer_tiers) | G2: resimac_customer_tiers | H2: 3.23 | I2: 1989 | J2: 0.000318
A3: RES-02 | B3: Resimac | C3: PRICING | D3: What is Resimac's interest rate for electric vehicles under the PremiumPLUS tier? | E3: v4: gpt-4o-mini + union retrieval (lender OR lender+intent) | F3: The interest rate for electric vehicles under the PremiumPLUS tier is **7.54%** per annum (chunk_id: resimac_interest_rates). | G3: resimac_interest_rates | H3: 3.22 | I3: 2337 | J3: 0.000364
A4: RES-03 | B4: Resimac | C4: PRICING | D4: What triggers a +2% risk loading at Resimac, and what is the maximum total risk loading per deal? | E4: v4: gpt-4o-mini + union retrieval (lender OR lender+intent) | F4: A +2% risk loading at Resimac applies to the following situations: - Private sales - Classic cars - Assets with age > 16 years at end of term - Prime movers This information is found in chunk_id **resimac_interest_rates**. The maximum total risk loading per deal is capped at **4%**. This information is also from chunk_id **resimac_interest_rates**. | G4: resimac_interest_rates | H4: 3.92 | I4: 2155 | J4: 0.000362
A5: RES-04 | B5: Resimac | C5: LOAN_LIMITS | D5: What is the maximum NAF for a Full Doc motor vehicle loan under Resimac's PremiumPLUS/Premium tier, and the per-passenger-vehicle cap? | E5: v4: gpt-4o-mini + union retrieval (lender OR lender+intent) | F5: The maximum NAF for a Full Doc motor vehicle loan under Resimac's PremiumPLUS tier is $450k (chunk_id: resimac_loan_limits). For the Premium tier, it is also $400k (chunk_id: resimac_loan_limits). Additionally, the per-passenger-vehicle cap for NAF is $250k (chunk_id: resimac_loan_limits). | G5: resimac_loan_limits | H5: 3.75 | I5: 2407 | J5: 0.000398
A6: RES-05 | B6: Resimac | C6: DOCUMENTATION | D6: Under Resimac's Lite Doc pathway, what are the ATO debt and turnover conditions? | E6: v4: gpt-4o-mini + union retrieval (lender OR lender+intent) | F6: Under Resimac's Lite Doc pathway, the ATO debt conditions are as follows: - ATO debt must be less than 10% of annual turnover (chunk_id: resimac_documentation). - ATO debt must be under an established payment arrangement that has been in place for more than 3 months (chunk_id: resimac_documentation). The turnover condition requires that BAS must show an annualised minimum turnover greater than 2.5 times the asset purchase price (chunk_id: resimac_documentation). | G6: resimac_documentation | H6: 4.77 | I6: 2527 | J6: 0.000428
A7: RES-06 | B7: Resimac | C7: ASSET_ELIGIBILITY | D7: How does Resimac classify a caravan, and what is the maximum asset age at end of term? | E7: v4: gpt-4o-mini + union retrieval (lender OR lender+intent) | F7: A caravan is classified as a **primary asset** (chunk_id: resimac_asset_categories). The maximum asset age at the end of the term for primary assets is **25 years** (chunk_id: resimac_asset_categories). | G7: resimac_asset_categories | H7: 3.82 | I7: 2466 | J7: 0.000391
A8: RES-07 | B8: Resimac | C8: EXCLUSIONS | D8: Can Resimac finance software or a food truck? | E8: v4: gpt-4o-mini + union retrieval (lender OR lender+intent) | F8: Resimac cannot finance software under any circumstances as it is listed as an excluded asset (chunk_id: resimac_exclusions). Additionally, a food truck is also an excluded asset and cannot be financed (chunk_id: resimac_exclusions). | G8: resimac_exclusions | H8: 1.61 | I8: 2203 | J8: 0.000353
A9: RES-08 | B9: Resimac | C9: FEES | D9: How does brokerage above 5.5% affect a Resimac deal, and what is the maximum brokerage? | E9: v4: gpt-4o-mini + union retrieval (lender OR lender+intent) | F9: Brokerage above 5.5% results in an equivalent of a 0.5% rate increase for every 1% increase in brokerage (or part thereof) (chunk_id: resimac_fees_brokerage). The maximum brokerage allowed is 8.8% (chunk_id: resimac_fees_brokerage). | G9: resimac_fees_brokerage | H9: 1.54 | I9: 2123 | J9: 0.00035
A10: RES-09 | B10: Resimac | C10: ELIGIBILITY | D10: If a Resimac applicant does not own property, what deposit is required? | E10: v4: gpt-4o-mini + union retrieval (lender OR lender+intent) | F10: If a Resimac applicant does not own property, a deposit of 10% is required for motor vehicles and 20% for all other assets. This information is sourced from the policy excerpts under "Non property-backed deposits." - 10% deposit required for motor vehicles (chunk_id: resimac_customer_tiers). - 20% deposit required for all other assets (chunk_id: resimac_customer_tiers). | G10: resimac_customer_tiers | H10: 2.08 | I10: 2253 | J10: 0.000377
A11: RES-10 | B11: Resimac | C11: SETTLEMENT | D11: When does Resimac require a Certificate of Currency? | E11: v4: gpt-4o-mini + union retrieval (lender OR lender+intent) | F11: Resimac requires a Certificate of Currency (proof of insurance) for NAF amounts greater than $100,000. (chunk_id: resimac_settlement) | G11: resimac_settlement | H11: 1.72 | I11: 1924 | J11: 0.000304
A12: RES-11 | B12: Resimac | C12: ELIGIBILITY | D12: What are the minimum Equifax credit scores for a Full Doc application at Resimac? | E12: v4: gpt-4o-mini + union retrieval (lender OR lender+intent) | F12: The minimum Equifax credit scores for a Full Doc application at Resimac are: - Sole Trader: ≥ 600 (chunk_id: resimac_customer_tiers) - Company / Guarantor: ≥ 550 (chunk_id: resimac_customer_tiers) Additionally, a score below 450 will result in a referral or decline (chunk_id: resimac_customer_tiers). | G12: resimac_customer_tiers | H12: 1.58 | I12: 2498 | J12: 0.000411
A13: RES-12 | B13: Resimac | C13: LOAN_LIMITS | D13: What is the maximum loan term at Resimac, including for electric vehicles? | E13: v4: gpt-4o-mini + union retrieval (lender OR lender+intent) | F13: The maximum loan term at Resimac is 60 months for Standard loans and up to 84 months for Green Goods (Electric Vehicles). This information comes from the policy excerpt with chunk_id [Source: resimac_loan_limits | Lender: RESIMAC]. | G13: resimac_loan_limits | H13: 1.29 | I13: 2211 | J13: 0.000356
... A176: FLX-25 | B176: Flexi | C176: ASSET_ELIGIBILITY | D176: How does flexicommercial classify medical and dental equipment? | E176: v4: gpt-4o-mini + union retrieval (lender OR lender+intent) | F176: Medical and dental equipment falls under the **Secondary assets** category at flexicommercial (chunk_id: flexi_asset_categories). | G176: flexi_asset_categories | H176: 0.93 | I176: 3610 | J176: 0.000553

Sheet Evaluation
A1: ID | B1: Lender | C1: Category | D1: Question | E1: Gold-Standard Answer (4/4) | F1: Model Answer (auto) | G1: Expected Chunk ID | H1: Retrieved Chunk ID (auto) | I1: Retrieval Hit (auto) | J1: Score (1-4) | K1: Score Rationale | L1: Reviewer | M1: Review Date
A2: RES-01 | B2: Resimac | C2: ELIGIBILITY | D2: What minimum ABN and GST registration duration does Resimac's PremiumPLUS tier require? | E2: Resimac's PremiumPLUS tier requires an ABN registered for more than 6 years and GST registered for more than 3 years. PremiumPLUS accepts property-backed borrowers only. | F2: =IFERROR(INDEX(ModelAnswers!$F$2:$F$176,MATCH($A2,ModelAnswers!$A$2:$A$176,0)),"") | G2: resimac_customer_tiers | H2: =IFERROR(INDEX(ModelAnswers!$G$2:$G$176,MATCH($A2,ModelAnswers!$A$2:$A$176,0)),"") | I2: =IF($H2="","",IF(EXACT(TRIM($G2),TRIM($H2)),1,0)) | J2: 4 | K2: Retrieval: HIT (expected resimac_customer_tiers, got ['resimac_customer_tiers', 'resimac_settlement', 'resimac_interest_rates', 'resimac_documentation', 'resimac_fees_brokerage']). Auto-scored via source-hit + gold-number-match + keyword-overlap heuristic (see tests/test_queries.py:score_answer). Human reviewer should verify.
A3: RES-02 | B3: Resimac | C3: PRICING | D3: What is Resimac's interest rate for electric vehicles under the PremiumPLUS tier? | E3: Electric vehicles are priced at 7.54% p.a. for PremiumPLUS clients (7.79% p.a. for Premium/Standard/Basic). This is the lowest rate in Resimac's range, and EVs also qualify for extended Green Goods terms up to 84 months. | F3: =IFERROR(INDEX(ModelAnswers!$F$2:$F$176,MATCH($A3,ModelAnswers!$A$2:$A$176,0)),"") | G3: resimac_interest_rates | H3: =IFERROR(INDEX(ModelAnswers!$G$2:$G$176,MATCH($A3,ModelAnswers!$A$2:$A$176,0)),"") | I3: =IF($H3="","",IF(EXACT(TRIM($G3),TRIM($H3)),1,0)) | J3: 2 | K3: Retrieval: HIT (expected resimac_interest_rates, got ['resimac_interest_rates', 'resimac_loan_limits', 'resimac_fees_brokerage', 'resimac_asset_categories', 'resimac_customer_tiers']). Auto-scored via source-hit + gold-number-match + keyword-overlap heuristic (see tests/test_queries.py:score_answer). Human reviewer should verify.
A4: RES-03 | B4: Resimac | C4: PRICING | D4: What triggers a +2% risk loading at Resimac, and what is the maximum total risk loading per deal? | E4: A +2% risk loading applies to each of: private sales, classic cars, assets with age over 16 years at end of term, and prime movers. Multiple loadings can stack, but the total risk loading is capped at 4% per deal (excluding brokerage loading). | F4: =IFERROR(INDEX(ModelAnswers!$F$2:$F$176,MATCH($A4,ModelAnswers!$A$2:$A$176,0)),"") | G4: resimac_interest_rates | H4: =IFERROR(INDEX(ModelAnswers!$G$2:$G$176,MATCH($A4,ModelAnswers!$A$2:$A$176,0)),"") | I4: =IF($H4="","",IF(EXACT(TRIM($G4),TRIM($H4)),1,0)) | J4: 4 | K4: Retrieval: HIT (expected resimac_interest_rates, got ['resimac_interest_rates', 'resimac_fees_brokerage', 'resimac_loan_limits', 'resimac_settlement', 'resimac_asset_categories']). Auto-scored via source-hit + gold-number-match + keyword-overlap heuristic (see tests/test_queries.py:score_answer). Human reviewer should verify.
A5: RES-04 | B5: Resimac | C5: LOAN_LIMITS | D5: What is the maximum NAF for a Full Doc motor vehicle loan under Resimac's PremiumPLUS/Premium tier, and the per-passenger-vehicle cap? | E5: Under PremiumPLUS/Premium, the maximum Full Doc NAF for motor vehicles is $450k. However, the maximum NAF per individual passenger vehicle is capped at $250k regardless of tier. | F5: =IFERROR(INDEX(ModelAnswers!$F$2:$F$176,MATCH($A5,ModelAnswers!$A$2:$A$176,0)),"") | G5: resimac_loan_limits | H5: =IFERROR(INDEX(ModelAnswers!$G$2:$G$176,MATCH($A5,ModelAnswers!$A$2:$A$176,0)),"") | I5: =IF($H5="","",IF(EXACT(TRIM($G5),TRIM($H5)),1,0)) | J5: 4 | K5: Retrieval: HIT (expected resimac_loan_limits, got ['resimac_loan_limits', 'resimac_interest_rates', 'resimac_asset_categories', 'resimac_customer_tiers', 'resimac_fees_brokerage']). Auto-scored via source-hit + gold-number-match + keyword-overlap heuristic (see tests/test_queries.py:score_answer). Human reviewer should verify.
A6: RES-05 | B6: Resimac | C6: DOCUMENTATION | D6: Under Resimac's Lite Doc pathway, what are the ATO debt and turnover conditions? | E6: For Lite Doc, ATO debt must be under 10% of annual turnover and under an established payment arrangement in place for more than 3 months. The BAS must show an annualised minimum turnover of more than 2.5x the asset purchase price. | F6: =IFERROR(INDEX(ModelAnswers!$F$2:$F$176,MATCH($A6,ModelAnswers!$A$2:$A$176,0)),"") | G6: resimac_documentation | H6: =IFERROR(INDEX(ModelAnswers!$G$2:$G$176,MATCH($A6,ModelAnswers!$A$2:$A$176,0)),"") | I6: =IF($H6="","",IF(EXACT(TRIM($G6),TRIM($H6)),1,0)) | J6: 4 | K6: Retrieval: HIT (expected resimac_documentation, got ['resimac_documentation', 'resimac_loan_limits', 'resimac_exclusions', 'resimac_customer_tiers', 'resimac_interest_rates']). Auto-scored via source-hit + gold-number-match + keyword-overlap heuristic (see tests/test_queries.py:score_answer). Human reviewer should verify.
A7: RES-06 | B7: Resimac | C7: ASSET_ELIGIBILITY | D7: How does Resimac classify a caravan, and what is the maximum asset age at end of term? | E7: A caravan is classified as a Primary Asset at Resimac. The maximum asset age at end of term for primary assets is 25 years. | F7: =IFERROR(INDEX(ModelAnswers!$F$2:$F$176,MATCH($A7,ModelAnswers!$A$2:$A$176,0)),"") | G7: resimac_asset_categories | H7: =IFERROR(INDEX(ModelAnswers!$G$2:$G$176,MATCH($A7,ModelAnswers!$A$2:$A$176,0)),"") | I7: =IF($H7="","",IF(EXACT(TRIM($G7),TRIM($H7)),1,0)) | J7: 4 | K7: Retrieval: HIT (expected resimac_asset_categories, got ['resimac_asset_categories', 'resimac_interest_rates', 'resimac_customer_tiers', 'resimac_loan_limits', 'resimac_exclusions']). Auto-scored via source-hit + gold-number-match + keyword-overlap heuristic (see tests/test_queries.py:score_answer). Human reviewer should verify.
A8: RES-07 | B8: Resimac | C8: EXCLUSIONS | D8: Can Resimac finance software or a food truck? | E8: No. Both software and food trucks are on Resimac's excluded assets list and cannot be financed under any circumstances, regardless of customer tier or documentation type. | F8: =IFERROR(INDEX(ModelAnswers!$F$2:$F$176,MATCH($A8,ModelAnswers!$A$2:$A$176,0)),"") | G8: resimac_exclusions | H8: =IFERROR(INDEX(ModelAnswers!$G$2:$G$176,MATCH($A8,ModelAnswers!$A$2:$A$176,0)),"") | I8: =IF($H8="","",IF(EXACT(TRIM($G8),TRIM($H8)),1,0)) | J8: 4 | K8: Retrieval: HIT (expected resimac_exclusions, got ['resimac_exclusions', 'resimac_loan_limits', 'resimac_asset_categories', 'resimac_interest_rates', 'resimac_fees_brokerage']). Auto-scored via source-hit + gold-number-match + keyword-overlap heuristic (see tests/test_queries.py:score_answer). Human reviewer should verify.
A9: RES-08 | B9: Resimac | C9: FEES | D9: How does brokerage above 5.5% affect a Resimac deal, and what is the maximum brokerage? | E9: Brokerage up to 5.5% (inclusive of GST) has no rate impact. Above 5.5%, the rate increases by the equivalent of 0.5% for every 1% of brokerage (or part thereof) above the threshold. Maximum brokerage is 8.8% inclusive of GST. | F9: =IFERROR(INDEX(ModelAnswers!$F$2:$F$176,MATCH($A9,ModelAnswers!$A$2:$A$176,0)),"") | G9: resimac_fees_brokerage | H9: =IFERROR(INDEX(ModelAnswers!$G$2:$G$176,MATCH($A9,ModelAnswers!$A$2:$A$176,0)),"") | I9: =IF($H9="","",IF(EXACT(TRIM($G9),TRIM($H9)),1,0)) | J9: 4 | K9: Retrieval: HIT (expected resimac_fees_brokerage, got ['resimac_fees_brokerage', 'resimac_interest_rates', 'resimac_loan_limits', 'resimac_customer_tiers', 'resimac_settlement']). Auto-scored via source-hit + gold-number-match + keyword-overlap heuristic (see tests/test_queries.py:score_answer). Human reviewer should verify.
A10: RES-09 | B10: Resimac | C10: ELIGIBILITY | D10: If a Resimac applicant does not own property, what deposit is required? | E10: For non property-backed applicants, a 10% deposit is required for motor vehicles and a 20% deposit is required for all other asset types. Spouse-owned property does not count as property backing but can waive a deposit if the borrower is legally married (not de facto). | F10: =IFERROR(INDEX(ModelAnswers!$F$2:$F$176,MATCH($A10,ModelAnswers!$A$2:$A$176,0)),"") | G10: resimac_customer_tiers | H10: =IFERROR(INDEX(ModelAnswers!$G$2:$G$176,MATCH($A10,ModelAnswers!$A$2:$A$176,0)),"") | I10: =IF($H10="","",IF(EXACT(TRIM($G10),TRIM($H10)),1,0)) | J10: 4 | K10: Retrieval: HIT (expected resimac_customer_tiers, got ['resimac_customer_tiers', 'resimac_settlement', 'resimac_documentation', 'resimac_exclusions', 'resimac_asset_categories']). Auto-scored via source-hit + gold-number-match + keyword-overlap heuristic (see tests/test_queries.py:score_answer). Human reviewer should verify.
A11: RES-10 | B11: Resimac | C11: SETTLEMENT | D11: When does Resimac require a Certificate of Currency? | E11: Resimac requires a Certificate of Currency (proof of insurance) for NAF amounts greater than $100k. Insurance is required on all deals regardless of size. | F11: =IFERROR(INDEX(ModelAnswers!$F$2:$F$176,MATCH($A11,ModelAnswers!$A$2:$A$176,0)),"") | G11: resimac_settlement | H11: =IFERROR(INDEX(ModelAnswers!$G$2:$G$176,MATCH($A11,ModelAnswers!$A$2:$A$176,0)),"") | I11: =IF($H11="","",IF(EXACT(TRIM($G11),TRIM($H11)),1,0)) | J11: 3 | K11: Retrieval: HIT (expected resimac_settlement, got ['resimac_settlement', 'resimac_documentation', 'resimac_customer_tiers', 'resimac_fees_brokerage', 'resimac_exclusions']). Auto-scored via source-hit + gold-number-match + keyword-overlap heuristic (see tests/test_queries.py:score_answer). Human reviewer should verify.
A12: RES-11 | B12: Resimac | C12: ELIGIBILITY | D12: What are the minimum Equifax credit scores for a Full Doc application at Resimac? | E12: For Full Doc, the minimum Equifax score is 600 for a sole trader and 550 for a company/guarantor. Any individual company or guarantor score below 450 results in referral to credit or decline. Resimac uses the highest score among the company or any guarantor as the assessment score. | F12: =IFERROR(INDEX(ModelAnswers!$F$2:$F$176,MATCH($A12,ModelAnswers!$A$2:$A$176,0)),"") | G12: resimac_customer_tiers | H12: =IFERROR(INDEX(ModelAnswers!$G$2:$G$176,MATCH($A12,ModelAnswers!$A$2:$A$176,0)),"") | I12: =IF($H12="","",IF(EXACT(TRIM($G12),TRIM($H12)),1,0)) | J12: 4 | K12: Retrieval: HIT (expected resimac_customer_tiers, got ['resimac_documentation', 'resimac_loan_limits', 'resimac_customer_tiers', 'resimac_exclusions', 'resimac_interest_rates']). Auto-scored via source-hit + gold-number-match + keyword-overlap heuristic (see tests/test_queries.py:score_answer). Human reviewer should verify.
A13: RES-12 | B13: Resimac | C13: LOAN_LIMITS | D13: What is the maximum loan term at Resimac, including for electric vehicles? | E13: Standard loan terms are 12-60 months. Green Goods (electric vehicles and sustainable assets) qualify for extended terms up to 84 months. | F13: =IFERROR(INDEX(ModelAnswers!$F$2:$F$176,MATCH($A13,ModelAnswers!$A$2:$A$176,0)),"") | G13: resimac_loan_limits | H13: =IFERROR(INDEX(ModelAnswers!$G$2:$G$176,MATCH($A13,ModelAnswers!$A$2:$A$176,0)),"") | I13: =IF($H13="","",IF(EXACT(TRIM($G13),TRIM($H13)),1,0)) | J13: 3 | K13: Retrieval: HIT (expected resimac_loan_limits, got ['resimac_loan_limits', 'resimac_interest_rates', 'resimac_asset_categories', 'resimac_fees_brokerage', 'resimac_exclusions']). Auto-scored via source-hit + gold-number-match + keyword-overlap heuristic (see tests/test_queries.py:score_answer). Human reviewer should verify.
... A176: FLX-25 | B176: Flexi | C176: ASSET_ELIGIBILITY | D176: How does flexicommercial classify medical and dental equipment? | E176: Medical / dental / laboratory equipment is classified as a secondary asset at flexicommercial. Secondary assets can be up to 7 years old at end of term. | F176: =IFERROR(INDEX(ModelAnswers!$F$2:$F$176,MATCH($A176,ModelAnswers!$A$2:$A$176,0)),"") | G176: flexi_asset_categories | H176: =IFERROR(INDEX(ModelAnswers!$G$2:$G$176,MATCH($A176,ModelAnswers!$A$2:$A$176,0)),"") | I176: =IF($H176="","",IF(EXACT(TRIM($G176),TRIM($H176)),1,0)) | J176: 2 | K176: Retrieval: HIT (expected flexi_asset_categories, got ['flexi_asset_categories', 'flexi_exclusions', 'flexi_flexipremium', 'flexi_refinance_products', 'flexi_credit_matrix', 'flexi_replacement_policy']). Auto-scored via source-hit + gold-number-match + keyword-overlap heuristic (see tests/test_queries.py:score_answer). Human reviewer should verify.

Sheet AccuracyReport
A1: Accuracy Report — auto-calculated
A3: HEADLINE METRICS | B3: Value | C3: Notes
A4: Questions scored | B4: =COUNT(Evaluation!$J$2:$J$176) | C4: Rows with a score entered
A5: Average score (out of 4) | B5: =IFERROR(AVERAGE(Evaluation!$J$2:$J$176),"—") | C5: Primary answer-quality metric
A6: Accuracy % | B6: =IFERROR(AVERAGE(Evaluation!$J$2:$J$176)/4,"—") | C6: Average score as a percentage of 4
A7: Retrieval hit rate | B7: =IFERROR(AVERAGE(Evaluation!$I$2:$I$176),"—") | C7: Did we fetch the expected chunk?
A8: Answers scored 4/4 | B8: =COUNTIF(Evaluation!$J$2:$J$176,4) | C8: Fully correct
A9: Answers scored 1/4 | B9: =COUNTIF(Evaluation!$J$2:$J$176,1) | C9: Completely wrong — investigate these first
A10: Hallucination rate | B10: =IFERROR(COUNTIF(Evaluation!$J$2:$J$176,1)/COUNT(Evaluation!$J$2:$J$176),"—") | C10: Share of completely-wrong answers
A11: Avg response time (s) | B11: =IFERROR(AVERAGE(ModelAnswers!$H$2:$H$176),"—") | C11: From ModelAnswers
A12: Total tokens | B12: =IFERROR(SUM(ModelAnswers!$I$2:$I$176),"—") | C12: From ModelAnswers
A13: Total est. cost (USD) | B13: =IFERROR(SUM(ModelAnswers!$J$2:$J$176),"—") | C13: From ModelAnswers
A15: SCORE DISTRIBUTION | B15: Count | C15: Share
A16: 4 — Completely right | B16: =COUNTIF(Evaluation!$J$2:$J$176,4) | C16: =IFERROR(B16/COUNT(Evaluation!$J$2:$J$176),"—")
A17: 3 — Minor mistakes | B17: =COUNTIF(Evaluation!$J$2:$J$176,3) | C17: =IFERROR(B17/COUNT(Evaluation!$J$2:$J$176),"—")
A18: 2 — Generally wrong | B18: =COUNTIF(Evaluation!$J$2:$J$176,2) | C18: =IFERROR(B18/COUNT(Evaluation!$J$2:$J$176),"—")
A19: 1 — Completely wrong | B19: =COUNTIF(Evaluation!$J$2:$J$176,1) | C19: =IFERROR(B19/COUNT(Evaluation!$J$2:$J$176),"—")
A21: BY LENDER | B21: Questions | C21: Avg Score | D21: Retrieval Hit Rate
A22: Resimac | B22: =COUNTIFS(Evaluation!$B$2:$B$176,"Resimac",Evaluation!$J$2:$J$176,">0") | C22: =IFERROR(AVERAGEIF(Evaluation!$B$2:$B$176,"Resimac",Evaluation!$J$2:$J$176),"—") | D22: =IFERROR(AVERAGEIF(Evaluation!$B$2:$B$176,"Resimac",Evaluation!$I$2:$I$176),"—")
A23: BFS | B23: =COUNTIFS(Evaluation!$B$2:$B$176,"BFS",Evaluation!$J$2:$J$176,">0") | C23: =IFERROR(AVERAGEIF(Evaluation!$B$2:$B$176,"BFS",Evaluation!$J$2:$J$176),"—") | D23: =IFERROR(AVERAGEIF(Evaluation!$B$2:$B$176,"BFS",Evaluation!$I$2:$I$176),"—")
A24: Westpac | B24: =COUNTIFS(Evaluation!$B$2:$B$176,"Westpac",Evaluation!$J$2:$J$176,">0") | C24: =IFERROR(AVERAGEIF(Evaluation!$B$2:$B$176,"Westpac",Evaluation!$J$2:$J$176),"—") | D24: =IFERROR(AVERAGEIF(Evaluation!$B$2:$B$176,"Westpac",Evaluation!$I$2:$I$176),"—")
A25: CFAL | B25: =COUNTIFS(Evaluation!$B$2:$B$176,"CFAL",Evaluation!$J$2:$J$176,">0") | C25: =IFERROR(AVERAGEIF(Evaluation!$B$2:$B$176,"CFAL",Evaluation!$J$2:$J$176),"—") | D25: =IFERROR(AVERAGEIF(Evaluation!$B$2:$B$176,"CFAL",Evaluation!$I$2:$I$176),"—")
A26: Angle | B26: =COUNTIFS(Evaluation!$B$2:$B$176,"Angle",Evaluation!$J$2:$J$176,">0") | C26: =IFERROR(AVERAGEIF(Evaluation!$B$2:$B$176,"Angle",Evaluation!$J$2:$J$176),"—") | D26: =IFERROR(AVERAGEIF(Evaluation!$B$2:$B$176,"Angle",Evaluation!$I$2:$I$176),"—")
A27: Metro | B27: =COUNTIFS(Evaluation!$B$2:$B$176,"Metro",Evaluation!$J$2:$J$176,">0") | C27: =IFERROR(AVERAGEIF(Evaluation!$B$2:$B$176,"Metro",Evaluation!$J$2:$J$176),"—") | D27: =IFERROR(AVERAGEIF(Evaluation!$B$2:$B$176,"Metro",Evaluation!$I$2:$I$176),"—")
A28: Flexi | B28: =COUNTIFS(Evaluation!$B$2:$B$176,"Flexi",Evaluation!$J$2:$J$176,">0") | C28: =IFERROR(AVERAGEIF(Evaluation!$B$2:$B$176,"Flexi",Evaluation!$J$2:$J$176),"—") | D28: =IFERROR(AVERAGEIF(Evaluation!$B$2:$B$176,"Flexi",Evaluation!$I$2:$I$176),"—")
A30: BY CATEGORY | B30: Questions | C30: Avg Score | D30: Retrieval Hit Rate
A31: ELIGIBILITY | B31: =COUNTIFS(Evaluation!$C$2:$C$176,"ELIGIBILITY",Evaluation!$J$2:$J$176,">0") | C31: =IFERROR(AVERAGEIF(Evaluation!$C$2:$C$176,"ELIGIBILITY",Evaluation!$J$2:$J$176),"—") | D31: =IFERROR(AVERAGEIF(Evaluation!$C$2:$C$176,"ELIGIBILITY",Evaluation!$I$2:$I$176),"—")
A32: PRICING | B32: =COUNTIFS(Evaluation!$C$2:$C$176,"PRICING",Evaluation!$J$2:$J$176,">0") | C32: =IFERROR(AVERAGEIF(Evaluation!$C$2:$C$176,"PRICING",Evaluation!$J$2:$J$176),"—") | D32: =IFERROR(AVERAGEIF(Evaluation!$C$2:$C$176,"PRICING",Evaluation!$I$2:$I$176),"—")
A33: LOAN_LIMITS | B33: =COUNTIFS(Evaluation!$C$2:$C$176,"LOAN_LIMITS",Evaluation!$J$2:$J$176,">0") | C33: =IFERROR(AVERAGEIF(Evaluation!$C$2:$C$176,"LOAN_LIMITS",Evaluation!$J$2:$J$176),"—") | D33: =IFERROR(AVERAGEIF(Evaluation!$C$2:$C$176,"LOAN_LIMITS",Evaluation!$I$2:$I$176),"—")
A34: DOCUMENTATION | B34: =COUNTIFS(Evaluation!$C$2:$C$176,"DOCUMENTATION",Evaluation!$J$2:$J$176,">0") | C34: =IFERROR(AVERAGEIF(Evaluation!$C$2:$C$176,"DOCUMENTATION",Evaluation!$J$2:$J$176),"—") | D34: =IFERROR(AVERAGEIF(Evaluation!$C$2:$C$176,"DOCUMENTATION",Evaluation!$I$2:$I$176),"—")
A35: ASSET_ELIGIBILITY | B35: =COUNTIFS(Evaluation!$C$2:$C$176,"ASSET_ELIGIBILITY",Evaluation!$J$2:$J$176,">0") | C35: =IFERROR(AVERAGEIF(Evaluation!$C$2:$C$176,"ASSET_ELIGIBILITY",Evaluation!$J$2:$J$176),"—") | D35: =IFERROR(AVERAGEIF(Evaluation!$C$2:$C$176,"ASSET_ELIGIBILITY",Evaluation!$I$2:$I$176),"—")
A36: EXCLUSIONS | B36: =COUNTIFS(Evaluation!$C$2:$C$176,"EXCLUSIONS",Evaluation!$J$2:$J$176,">0") | C36: =IFERROR(AVERAGEIF(Evaluation!$C$2:$C$176,"EXCLUSIONS",Evaluation!$J$2:$J$176),"—") | D36: =IFERROR(AVERAGEIF(Evaluation!$C$2:$C$176,"EXCLUSIONS",Evaluation!$I$2:$I$176),"—")
A37: SETTLEMENT | B37: =COUNTIFS(Evaluation!$C$2:$C$176,"SETTLEMENT",Evaluation!$J$2:$J$176,">0") | C37: =IFERROR(AVERAGEIF(Evaluation!$C$2:$C$176,"SETTLEMENT",Evaluation!$J$2:$J$176),"—") | D37: =IFERROR(AVERAGEIF(Evaluation!$C$2:$C$176,"SETTLEMENT",Evaluation!$I$2:$I$176),"—")
A38: SPECIAL_PROGRAMS | B38: =COUNTIFS(Evaluation!$C$2:$C$176,"SPECIAL_PROGRAMS",Evaluation!$J$2:$J$176,">0") | C38: =IFERROR(AVERAGEIF(Evaluation!$C$2:$C$176,"SPECIAL_PROGRAMS",Evaluation!$J$2:$J$176),"—") | D38: =IFERROR(AVERAGEIF(Evaluation!$C$2:$C$176,"SPECIAL_PROGRAMS",Evaluation!$I$2:$I$176),"—")
A39: FEES | B39: =COUNTIFS(Evaluation!$C$2:$C$176,"FEES",Evaluation!$J$2:$J$176,">0") | C39: =IFERROR(AVERAGEIF(Evaluation!$C$2:$C$176,"FEES",Evaluation!$J$2:$J$176),"—") | D39: =IFERROR(AVERAGEIF(Evaluation!$C$2:$C$176,"FEES",Evaluation!$I$2:$I$176),"—")

Sheet RAG_Comparison
A1: Config ID | B1: Variable Tested | C1: Setting | D1: Avg Score (/4) | E1: Accuracy % | F1: Retrieval Hit Rate | G1: Hallucination Rate | H1: Avg Response Time (s) | I1: Total Tokens | J1: Est. Cost (USD) | K1: Verdict / Notes
A2: C1 | B2: Top-K Retrieval | C2: Top-K = 3
A3: C2 | B3: Top-K Retrieval | C3: Top-K = 5 | D3: 3.09 | E3: 0.7725 | F3: 0.989 | H3: 2.08 | I3: 423454 | J3: 0.0679 | K3: Actual measured config (gpt-4o-mini, union retrieval: lender OR lender+intent, lender-detection priority fix). Hallucination rate not measured - no detection methodology implemented this round. Other rows (Top-K=3, Top-K=10, Prompt v2) not yet run - would need separate benchmark passes at those settings.
A4: C3 | B4: Top-K Retrieval | C4: Top-K = 10
A5: C4 | B5: Prompt Template | C5: Baseline prompt
A6: C5 | B6: Prompt Template | C6: Prompt v2 (strict citation)
A7: C6 | B7: Prompt Template | C7: Prompt v3 (refuse if unsure)
A8: C7 | B8: Metadata Filtering | C8: Filtering ON
A9: C8 | B9: Metadata Filtering | C9: Filtering OFF (control)
A10: C9 | B10: Chunk Size | C10: Default chunks
A11: C10 | B11: Chunk Size | C11: Smaller chunks
A13: How to use: run the 100-question benchmark once per config. Copy the headline numbers from 'AccuracyReport' into the row for that config. The best average score highlights green automatically.

Sheet ErrorLog
A1: ID | B1: Lender | C1: Score | D1: Failure Type | E1: What went wrong | F1: Root cause | G1: Fix / owner | H1: Status
A2: (example) CFA-07 | B2: CFAL | C2: 1 | D2: Cross-lender contamination | E2: Answered with a Westpac DriveXpress limit | F2: Shared 'DriveXpress' keyword routed to WESTPAC | G2: Add lender keyword weighting — Sameep | H2: Open
A21: CFA-03, CFA-12, CFA-18, CFA-22 | B21: CFAL | C21: 1 | D21: Cross-lender contamination | E21: Questions mentioning both 'CFAL' and 'DriveXpress' were answered from Westpac's DriveXpress chunks instead of CFAL's | F21: detect_lender() checked lenders in fixed dict order (Westpac first); CFAL's own product name 'DriveXpress' contains the substring 'xpress', which is also a Westpac keyword, so Westpac matched first regardless of the explicit 'CFAL' mention | G21: Reordered detect_lender() to check each lender's exact name first (pass 1) before any lender's secondary/product keywords (pass 2) - Claude | H21: Fixed
A22: BFS-21 | B22: BFS | C22: 2 | D22: Retrieval ranking miss | E22: Correct chunk (bfs_customer_tiers) not retrieved | F22: Chunk ranks 7th of 9 BFS chunks by embedding similarity - outside top-5 - question phrasing has weaker semantic overlap with that chunk than several unrelated BFS chunks | G22: None applied. Would require raising TOP_K (context/cost tradeoff) or a reranking step. Left as a known limitation rather than adding an overfit keyword patch. | H22: Open
A23: FLX-17 | B23: Flexi | C23: 2 | D23: Retrieval ranking miss | E23: Correct chunk (flexi_asset_categories) not retrieved | F23: 'maximum exposure for IT assets' pulls toward flexi_credit_matrix (a LOAN_LIMITS chunk about exposure caps generally); a keyword fix broad enough to catch this would also wrongly reclassify FLX-05, which legitimately is LOAN_LIMITS | G23: None applied - rejected as overfitting risk. Same phrase pattern maps to different gold intents depending on context; not resolvable via keyword matching alone. | H23: Open
A24: Metro category (25 Q) | B24: Metro | C24: 2 | D24: Answer-quality ceiling (not retrieval) | E24: Most Metro questions retrieve the correct chunk (source hit) but the model's answer doesn't reproduce enough of the gold numbers to score above 2-3 | F24: Metro's chunks are dense markdown rate/limit tables (multiple numeric columns per row); gpt-4o-mini answers tend to summarize rather than enumerate every figure | G24: Not addressed this round. Candidate fixes: stricter prompt instruction to quote every number verbatim, or pre-flattening tables before embedding. | H24: Open
A25: FEES category (8 Q) / SETTLEMENT category (7 Q) | B25: All | C25: 2 | D25: Answer-quality ceiling (not retrieval) | E25: Both categories have 100% retrieval hit rate already, but average only 2.50-2.71/4 | F25: Same root cause as Metro - answer generation, not retrieval/routing. Confirmed via diagnostic: every FEES and SETTLEMENT question retrieves its expected chunk. | G25: Not addressed this round - flagged for prompt-engineering follow-up, since no retrieval/keyword fix applies here. | H25: Open
